odoo10_addon_website_event_require_login-10.0.1.0.0.99.dev7-py3.8-nspkg.pth
odoo/addons/website_event_require_login/README.rst
odoo/addons/website_event_require_login/__init__.py
odoo/addons/website_event_require_login/__manifest__.py
odoo/addons/website_event_require_login/controllers/__init__.py
odoo/addons/website_event_require_login/controllers/main.py
odoo/addons/website_event_require_login/i18n/de.po
odoo/addons/website_event_require_login/i18n/es.po
odoo/addons/website_event_require_login/i18n/website_event_require_login.pot
odoo/addons/website_event_require_login/models/__init__.py
odoo/addons/website_event_require_login/models/event.py
odoo/addons/website_event_require_login/readme/CONFIGURE.rst
odoo/addons/website_event_require_login/readme/CONTRIBUTORS.rst
odoo/addons/website_event_require_login/readme/DESCRIPTION.rst
odoo/addons/website_event_require_login/readme/ROADMAP.rst
odoo/addons/website_event_require_login/readme/USAGE.rst
odoo/addons/website_event_require_login/static/description/icon.png
odoo/addons/website_event_require_login/static/description/index.html
odoo/addons/website_event_require_login/views/event_views.xml
odoo/addons/website_event_require_login/views/website_event_templates.xml
odoo10_addon_website_event_require_login-10.0.1.0.0.99.dev7.dist-info/METADATA
odoo10_addon_website_event_require_login-10.0.1.0.0.99.dev7.dist-info/WHEEL
odoo10_addon_website_event_require_login-10.0.1.0.0.99.dev7.dist-info/namespace_packages.txt
odoo10_addon_website_event_require_login-10.0.1.0.0.99.dev7.dist-info/top_level.txt
odoo10_addon_website_event_require_login-10.0.1.0.0.99.dev7.dist-info/RECORD
